Metadata-Version: 2.1
Name: atsocatest
Version: 0.0.4
Summary: An easy and funny example of a Python package
Home-page: UNKNOWN
Author: Carlos Acosta
Author-email: atsoca.c@gmail.com
License: UNKNOWN
Platform: UNKNOWN
Classifier: Programming Language :: Python :: 3
Classifier: License :: OSI Approved :: MIT License
Classifier: Operating System :: OS Independent
Requires-Python: >=3.6
License-File: licence.txt
